{"children":[{"children":[{"children":[{"children":[],"text":"","order":"4","name":"It"}],"text":" It","order":"3","name":"PRP"}],"text":" It","order":"2","name":"NP"},{"children":[{"children":[{"children":[{"children":[],"text":"","order":"8","name":"invests"}],"text":" invests","order":"7","name":"VBZ"},{"children":[{"children":[{"children":[],"text":"","order":"11","name":"heavily"}],"text":" heavily","order":"10","name":"RB"}],"text":" heavily","order":"9","name":"ADVP"},{"children":[{"children":[{"children":[],"text":"","order":"14","name":"in"}],"text":" in","order":"13","name":"IN"},{"children":[{"children":[{"children":[{"children":[],"text":"","order":"18","name":"dollar-denominated"}],"text":" dollar-denominated","order":"17","name":"JJ"},{"children":[{"children":[],"text":"","order":"20","name":"securities"}],"text":" securities","order":"19","name":"NNS"}],"text":" dollar-denominated securities","order":"16","name":"NP"},{"children":[{"children":[{"children":[],"text":"","order":"23","name":"overseas"}],"text":" overseas","order":"22","name":"RB"}],"text":" overseas","order":"21","name":"ADVP"}],"text":" dollar-denominated securities overseas","order":"15","name":"NP"}],"text":" in dollar-denominated securities overseas","order":"12","name":"PP"}],"text":" invests heavily in dollar-denominated securities overseas","order":"6","name":"VP"},{"children":[{"children":[],"text":"","order":"25","name":"and"}],"text":" and","order":"24","name":"CC"},{"children":[{"children":[{"children":[],"text":"","order":"28","name":"is"}],"text":" is","order":"27","name":"VBZ"},{"children":[{"children":[{"children":[],"text":"","order":"31","name":"currently"}],"text":" currently","order":"30","name":"RB"}],"text":" currently","order":"29","name":"ADVP"},{"children":[{"children":[{"children":[{"children":[],"text":"","order":"35","name":"waiving"}],"text":" waiving","order":"34","name":"VBG"},{"children":[{"children":[{"children":[],"text":"","order":"38","name":"management"}],"text":" management","order":"37","name":"NN"},{"children":[{"children":[],"text":"","order":"40","name":"fees"}],"text":" fees","order":"39","name":"NNS"}],"text":" management fees","order":"36","name":"NP"}],"text":" waiving management fees","order":"33","name":"VP"},{"children":[{"children":[],"text":"","order":"42","name":","}],"text":" ,","order":"41","name":","},{"children":[{"children":[{"children":[{"children":[],"text":"","order":"46","name":"which"}],"text":" which","order":"45","name":"WDT"}],"text":" which","order":"44","name":"WHNP"},{"children":[{"children":[{"children":[{"children":[],"text":"","order":"50","name":"boosts"}],"text":" boosts","order":"49","name":"VBZ"},{"children":[{"children":[{"children":[],"text":"","order":"53","name":"its"}],"text":" its","order":"52","name":"PRP$"},{"children":[{"children":[],"text":"","order":"55","name":"yield"}],"text":" yield","order":"54","name":"NN"}],"text":" its yield","order":"51","name":"NP"}],"text":" boosts its yield","order":"48","name":"VP"}],"text":" boosts its yield","order":"47","name":"S"}],"text":" which boosts its yield","order":"43","name":"SBAR"}],"text":" waiving management fees , which boosts its yield","order":"32","name":"VP"}],"text":" is currently waiving management fees , which boosts its yield","order":"26","name":"VP"}],"text":" invests heavily in dollar-denominated securities overseas and is currently waiving management fees , which boosts its yield","order":"5","name":"VP"},{"children":[{"children":[],"text":"","order":"57","name":"."}],"text":" .","order":"56","name":"."}],"text":" It invests heavily in dollar-denominated securities overseas and is currently waiving management fees , which boosts its yield .","order":"1","name":"S"}