{"children":[{"children":[{"children":[],"text":"","order":"3","name":"``"}],"text":" ``","order":"2","name":"``"},{"children":[{"children":[{"children":[{"children":[],"text":"","order":"7","name":"The"}],"text":" The","order":"6","name":"DT"},{"children":[{"children":[],"text":"","order":"9","name":"morbidity"}],"text":" morbidity","order":"8","name":"NN"},{"children":[{"children":[],"text":"","order":"11","name":"rate"}],"text":" rate","order":"10","name":"NN"}],"text":" The morbidity rate","order":"5","name":"NP"},{"children":[{"children":[{"children":[],"text":"","order":"14","name":"is"}],"text":" is","order":"13","name":"VBZ"},{"children":[{"children":[{"children":[{"children":[],"text":"","order":"18","name":"a"}],"text":" a","order":"17","name":"DT"},{"children":[{"children":[],"text":"","order":"20","name":"striking"}],"text":" striking","order":"19","name":"JJ"},{"children":[{"children":[],"text":"","order":"22","name":"finding"}],"text":" finding","order":"21","name":"NN"}],"text":" a striking finding","order":"16","name":"NP"},{"children":[{"children":[{"children":[],"text":"","order":"25","name":"among"}],"text":" among","order":"24","name":"IN"},{"children":[{"children":[{"children":[{"children":[],"text":"","order":"29","name":"those"}],"text":" those","order":"28","name":"DT"}],"text":" those","order":"27","name":"NP"},{"children":[{"children":[{"children":[],"text":"","order":"32","name":"of"}],"text":" of","order":"31","name":"IN"},{"children":[{"children":[{"children":[],"text":"","order":"35","name":"us"}],"text":" us","order":"34","name":"PRP"}],"text":" us","order":"33","name":"NP"}],"text":" of us","order":"30","name":"PP"},{"children":[{"children":[{"children":[{"children":[],"text":"","order":"39","name":"who"}],"text":" who","order":"38","name":"WP"}],"text":" who","order":"37","name":"WHNP"},{"children":[{"children":[{"children":[{"children":[],"text":"","order":"43","name":"study"}],"text":" study","order":"42","name":"VBP"},{"children":[{"children":[{"children":[],"text":"","order":"46","name":"asbestos-related"}],"text":" asbestos-related","order":"45","name":"JJ"},{"children":[{"children":[],"text":"","order":"48","name":"diseases"}],"text":" diseases","order":"47","name":"NNS"}],"text":" asbestos-related diseases","order":"44","name":"NP"}],"text":" study asbestos-related diseases","order":"41","name":"VP"}],"text":" study asbestos-related diseases","order":"40","name":"S"}],"text":" who study asbestos-related diseases","order":"36","name":"SBAR"}],"text":" those of us who study asbestos-related diseases","order":"26","name":"NP"}],"text":" among those of us who study asbestos-related diseases","order":"23","name":"PP"}],"text":" a striking finding among those of us who study asbestos-related diseases","order":"15","name":"NP"}],"text":" is a striking finding among those of us who study asbestos-related diseases","order":"12","name":"VP"}],"text":" The morbidity rate is a striking finding among those of us who study asbestos-related diseases","order":"4","name":"S"},{"children":[{"children":[],"text":"","order":"50","name":","}],"text":" ,","order":"49","name":","},{"children":[{"children":[],"text":"","order":"52","name":"''"}],"text":" ''","order":"51","name":"''"},{"children":[{"children":[{"children":[],"text":"","order":"55","name":"said"}],"text":" said","order":"54","name":"VBD"}],"text":" said","order":"53","name":"VP"},{"children":[{"children":[{"children":[],"text":"","order":"58","name":"Dr."}],"text":" Dr.","order":"57","name":"NNP"},{"children":[{"children":[],"text":"","order":"60","name":"Talcott"}],"text":" Talcott","order":"59","name":"NNP"}],"text":" Dr. Talcott","order":"56","name":"NP"},{"children":[{"children":[],"text":"","order":"62","name":"."}],"text":" .","order":"61","name":"."}],"text":" `` The morbidity rate is a striking finding among those of us who study asbestos-related diseases , '' said Dr. Talcott .","order":"1","name":"SINV"}