{"children":[{"children":[{"children":[],"text":"","order":"3","name":"More"}],"text":" More","order":"2","name":"JJR"},{"children":[{"children":[{"children":[],"text":"","order":"6","name":"than"}],"text":" than","order":"5","name":"IN"},{"children":[{"children":[{"children":[{"children":[],"text":"","order":"10","name":"a"}],"text":" a","order":"9","name":"DT"},{"children":[{"children":[],"text":"","order":"12","name":"few"}],"text":" few","order":"11","name":"JJ"},{"children":[{"children":[],"text":"","order":"14","name":"CEOs"}],"text":" CEOs","order":"13","name":"NNS"}],"text":" a few CEOs","order":"8","name":"NP"},{"children":[{"children":[{"children":[],"text":"","order":"17","name":"say"}],"text":" say","order":"16","name":"VBP"},{"children":[{"children":[{"children":[{"children":[{"children":[],"text":"","order":"22","name":"the"}],"text":" the","order":"21","name":"DT"},{"children":[{"children":[],"text":"","order":"24","name":"red-carpet"}],"text":" red-carpet","order":"23","name":"JJ"},{"children":[{"children":[],"text":"","order":"26","name":"treatment"}],"text":" treatment","order":"25","name":"NN"}],"text":" the red-carpet treatment","order":"20","name":"NP"},{"children":[{"children":[{"children":[],"text":"","order":"29","name":"tempts"}],"text":" tempts","order":"28","name":"VBZ"},{"children":[{"children":[{"children":[{"children":[],"text":"","order":"33","name":"them"}],"text":" them","order":"32","name":"PRP"}],"text":" them","order":"31","name":"NP"},{"children":[{"children":[{"children":[],"text":"","order":"36","name":"to"}],"text":" to","order":"35","name":"TO"},{"children":[{"children":[{"children":[],"text":"","order":"39","name":"return"}],"text":" return","order":"38","name":"VB"},{"children":[{"children":[{"children":[],"text":"","order":"42","name":"to"}],"text":" to","order":"41","name":"TO"},{"children":[{"children":[{"children":[{"children":[],"text":"","order":"46","name":"a"}],"text":" a","order":"45","name":"DT"},{"children":[{"children":[],"text":"","order":"48","name":"heartland"}],"text":" heartland","order":"47","name":"JJ"},{"children":[{"children":[],"text":"","order":"50","name":"city"}],"text":" city","order":"49","name":"NN"}],"text":" a heartland city","order":"44","name":"NP"},{"children":[{"children":[{"children":[],"text":"","order":"53","name":"for"}],"text":" for","order":"52","name":"IN"},{"children":[{"children":[{"children":[],"text":"","order":"56","name":"future"}],"text":" future","order":"55","name":"JJ"},{"children":[{"children":[],"text":"","order":"58","name":"meetings"}],"text":" meetings","order":"57","name":"NNS"}],"text":" future meetings","order":"54","name":"NP"}],"text":" for future meetings","order":"51","name":"PP"}],"text":" a heartland city for future meetings","order":"43","name":"NP"}],"text":" to a heartland city for future meetings","order":"40","name":"PP"}],"text":" return to a heartland city for future meetings","order":"37","name":"VP"}],"text":" to return to a heartland city for future meetings","order":"34","name":"VP"}],"text":" them to return to a heartland city for future meetings","order":"30","name":"S"}],"text":" tempts them to return to a heartland city for future meetings","order":"27","name":"VP"}],"text":" the red-carpet treatment tempts them to return to a heartland city for future meetings","order":"19","name":"S"}],"text":" the red-carpet treatment tempts them to return to a heartland city for future meetings","order":"18","name":"SBAR"}],"text":" say the red-carpet treatment tempts them to return to a heartland city for future meetings","order":"15","name":"VP"}],"text":" a few CEOs say the red-carpet treatment tempts them to return to a heartland city for future meetings","order":"7","name":"S"}],"text":" than a few CEOs say the red-carpet treatment tempts them to return to a heartland city for future meetings","order":"4","name":"SBAR"},{"children":[{"children":[],"text":"","order":"60","name":"."}],"text":" .","order":"59","name":"."}],"text":" More than a few CEOs say the red-carpet treatment tempts them to return to a heartland city for future meetings .","order":"1","name":"ADJP"}