{"children":[{"children":[{"children":[{"children":[],"text":"","order":"4","name":"The"}],"text":" The","order":"3","name":"DT"},{"children":[{"children":[],"text":"","order":"6","name":"Treasury"}],"text":" Treasury","order":"5","name":"NNP"}],"text":" The Treasury","order":"2","name":"NP"},{"children":[{"children":[{"children":[],"text":"","order":"9","name":"said"}],"text":" said","order":"8","name":"VBD"},{"children":[{"children":[{"children":[{"children":[{"children":[],"text":"","order":"14","name":"the"}],"text":" the","order":"13","name":"DT"},{"children":[{"children":[],"text":"","order":"16","name":"U.S."}],"text":" U.S.","order":"15","name":"NNP"}],"text":" the U.S.","order":"12","name":"NP"},{"children":[{"children":[{"children":[],"text":"","order":"19","name":"will"}],"text":" will","order":"18","name":"MD"},{"children":[{"children":[{"children":[],"text":"","order":"22","name":"default"}],"text":" default","order":"21","name":"VB"},{"children":[{"children":[{"children":[],"text":"","order":"25","name":"on"}],"text":" on","order":"24","name":"IN"},{"children":[{"children":[{"children":[],"text":"","order":"28","name":"Nov."}],"text":" Nov.","order":"27","name":"NNP"},{"children":[{"children":[],"text":"","order":"30","name":"9"}],"text":" 9","order":"29","name":"CD"}],"text":" Nov. 9","order":"26","name":"NP"}],"text":" on Nov. 9","order":"23","name":"PP"},{"children":[{"children":[{"children":[],"text":"","order":"33","name":"if"}],"text":" if","order":"32","name":"IN"},{"children":[{"children":[{"children":[{"children":[],"text":"","order":"37","name":"Congress"}],"text":" Congress","order":"36","name":"NNP"}],"text":" Congress","order":"35","name":"NP"},{"children":[{"children":[{"children":[],"text":"","order":"40","name":"does"}],"text":" does","order":"39","name":"VBZ"},{"children":[{"children":[],"text":"","order":"42","name":"n't"}],"text":" n't","order":"41","name":"RB"},{"children":[{"children":[{"children":[],"text":"","order":"45","name":"act"}],"text":" act","order":"44","name":"VB"},{"children":[{"children":[{"children":[],"text":"","order":"48","name":"by"}],"text":" by","order":"47","name":"IN"},{"children":[{"children":[{"children":[],"text":"","order":"51","name":"then"}],"text":" then","order":"50","name":"RB"}],"text":" then","order":"49","name":"ADVP"}],"text":" by then","order":"46","name":"PP"}],"text":" act by then","order":"43","name":"VP"}],"text":" does n't act by then","order":"38","name":"VP"}],"text":" Congress does n't act by then","order":"34","name":"S"}],"text":" if Congress does n't act by then","order":"31","name":"SBAR"}],"text":" default on Nov. 9 if Congress does n't act by then","order":"20","name":"VP"}],"text":" will default on Nov. 9 if Congress does n't act by then","order":"17","name":"VP"}],"text":" the U.S. will default on Nov. 9 if Congress does n't act by then","order":"11","name":"S"}],"text":" the U.S. will default on Nov. 9 if Congress does n't act by then","order":"10","name":"SBAR"}],"text":" said the U.S. will default on Nov. 9 if Congress does n't act by then","order":"7","name":"VP"},{"children":[{"children":[],"text":"","order":"53","name":"."}],"text":" .","order":"52","name":"."}],"text":" The Treasury said the U.S. will default on Nov. 9 if Congress does n't act by then .","order":"1","name":"S"}